np_struct/__init__.py
np_struct/fields.py
np_struct/ldarray.py
np_struct/structures.py
np_struct/transfer.py
np_struct-0.0.2.dist-info/METADATA
np_struct-0.0.2.dist-info/WHEEL
np_struct-0.0.2.dist-info/top_level.txt
np_struct-0.0.2.dist-info/RECORD
