Metadata-Version: 2.4
Name: np-struct
Version: 0.0.2
Summary: Interface for NumPy structured arrays
Author-email: Rick Lyon <rlyon14@gmail.com>
Project-URL: repository, https://github.com/ricklyon/np_struct
Keywords: numpy,structured array,struct
Classifier: License :: OSI Approved :: MIT License
Classifier: Programming Language :: Python
Classifier: Programming Language :: Python :: 3
Requires-Python: >=3.7
Requires-Dist: numpy
Provides-Extra: dev
Requires-Dist: black; extra == "dev"
Requires-Dist: flake8; extra == "dev"
Requires-Dist: pytest; extra == "dev"
